hut_services/__init__.py
hut_services/py.typed
hut_services/services.py
hut_services/core/__init__.py
hut_services/core/cache.py
hut_services/core/guess.py
hut_services/core/schema/__init__.py
hut_services/core/schema/_base.py
hut_services/core/schema/_booking.py
hut_services/core/schema/_contact.py
hut_services/core/schema/_hut.py
hut_services/core/schema/_hut_base_converter.py
hut_services/core/schema/_hut_base_source.py
hut_services/core/schema/_hut_fields.py
hut_services/core/schema/_license.py
hut_services/core/schema/_photo.py
hut_services/core/schema/locale.py
hut_services/core/schema/geo/__init__.py
hut_services/core/schema/geo/bbox.py
hut_services/core/schema/geo/geo.py
hut_services/core/schema/geo/types.py
hut_services/core/service/__init__.py
hut_services/core/service/_service_base.py
hut_services/core/utils/__init__.py
hut_services/core/utils/_gps_converter.py
hut_services/geocode/__init__.py
hut_services/geocode/schema.py
hut_services/geocode/script.py
hut_services/geocode/service.py
hut_services/osm/__init__.py
hut_services/osm/coordinates.py
hut_services/osm/exceptions.py
hut_services/osm/schema.py
hut_services/osm/service.py
hut_services/refuges_info/__init__.py
hut_services/refuges_info/coordinates.py
hut_services/refuges_info/exceptions.py
hut_services/refuges_info/massif.py
hut_services/refuges_info/schema.py
hut_services/refuges_info/service.py
hut_services/refuges_info/utils.py
hut_services/wikicommons/__init__.py
hut_services/wikicommons/service.py
hut_services/wikidata/__init__.py
hut_services/wikidata/schema.py
hut_services/wikidata/script.py
hut_services/wikidata/service.py
hut_services/wikipedia/README.adoc
hut_services-0.1.3.dist-info/METADATA
hut_services-0.1.3.dist-info/WHEEL
hut_services-0.1.3.dist-info/licenses/LICENSE
hut_services-0.1.3.dist-info/RECORD
